folder_vision/__init__.py
folder_vision/__main__.py
folder_vision/app.py
folder_vision/cli.py
folder_vision/clip_search.py
folder_vision/html/cluster.html
folder_vision/html/gallery.html
folder_vision/html/home.html
folder_vision/html/index.html
folder_vision/html/results.html
folder_vision/html/search.html
folder_vision/static/css/styles.css
folder_vision/static/css/visualization.css
folder_vision/static/js/app.js
folder_vision-1.0.0.dist-info/licenses/LICENSE
folder_vision-1.0.0.dist-info/METADATA
folder_vision-1.0.0.dist-info/WHEEL
folder_vision-1.0.0.dist-info/entry_points.txt
folder_vision-1.0.0.dist-info/top_level.txt
folder_vision-1.0.0.dist-info/RECORD
