Metadata-Version: 2.4
Name: folder-vision
Version: 1.0.0
Summary: CLIP-powered multimodal image search engine with web interface and CLI tools
Author-email: Folder Vision Team <team@foldervision.dev>
License-Expression: MIT
Project-URL: Homepage, https://github.com/folder-vision/folder-vision
Project-URL: Repository, https://github.com/folder-vision/folder-vision
Project-URL: Issues, https://github.com/folder-vision/folder-vision/issues
Project-URL: Documentation, https://github.com/folder-vision/folder-vision#readme
Keywords: clip,image-search,multimodal,ai,computer-vision,fastapi,search-engine,similarity-search,image-clustering
Classifier: Development Status :: 5 - Production/Stable
Classifier: Intended Audience :: Developers
Classifier: Intended Audience :: End Users/Desktop
Classifier: Intended Audience :: Science/Research
Classifier: Operating System :: OS Independent
Classifier: Programming Language :: Python :: 3
Classifier: Programming Language :: Python :: 3.9
Classifier: Programming Language :: Python :: 3.10
Classifier: Programming Language :: Python :: 3.11
Classifier: Programming Language :: Python :: 3.12
Classifier: Topic :: Scientific/Engineering :: Artificial Intelligence
Classifier: Topic :: Scientific/Engineering :: Image Processing
Classifier: Topic :: Multimedia :: Graphics
Classifier: Topic :: Internet :: WWW/HTTP :: HTTP Servers
Classifier: Topic :: Software Development :: Libraries :: Application Frameworks
Classifier: Framework :: FastAPI
Requires-Python: >=3.9
License-File: LICENSE
Requires-Dist: fastapi<1.0.0,>=0.100.0
Requires-Dist: uvicorn[standard]<1.0.0,>=0.25.0
Requires-Dist: torch>=2.0.0
Requires-Dist: torchvision>=0.15.0
Requires-Dist: transformers>=4.30.0
Requires-Dist: pillow>=9.0.0
Requires-Dist: numpy>=1.21.0
Requires-Dist: python-multipart>=0.0.6
Requires-Dist: scikit-learn>=1.0.0
Requires-Dist: matplotlib>=3.0.0
Requires-Dist: plotly>=5.0.0
Provides-Extra: dev
Requires-Dist: pytest>=7.0; extra == "dev"
Requires-Dist: pytest-cov>=4.0; extra == "dev"
Requires-Dist: httpx>=0.25; extra == "dev"
Dynamic: license-file
